{
  "_class": "group",
  "do_objectID": "C5759F34-C833-412D-8116-ECFEABD04311",
  "exportOptions": {
    "_class": "exportOptions",
    "exportFormats": [
    ],
    "includedLayerIds": [
    ],
    "layerOptions": 0,
    "shouldTrim": false
  },
  "frame": {
    "_class": "rect",
    "constrainProportions": false,
    "height": 207,
    "width": 425,
    "x": 352,
    "y": 267
  },
  "hasClickThrough": false,
  "isFlippedHorizontal": false,
  "isFlippedVertical": false,
  "isLocked": false,
  "isVisible": true,
  "layerListExpandedType": 0,
  "layers": [
    {
      "class": "shapeGroup",
      "id": "060B2252-21D1-4512-87FE-9F37C35C1B09"
    },
    {
      "class": "text",
      "id": "F719E768-9B4B-459C-BC37-D88254D81947"
    },
    {
      "class": "shapeGroup",
      "id": "82A67E03-F7F3-4381-B715-5DAAD6D6B06A"
    },
    {
      "class": "text",
      "id": "20A0DF7A-BCFD-4515-9782-E16680BB4E41"
    },
    {
      "class": "shapeGroup",
      "id": "50B6953E-8819-4792-9E0A-6A2E2C2E32C9"
    },
    {
      "class": "text",
      "id": "0154CF49-153F-43A3-83F2-BB1A87D25262"
    },
    {
      "class": "shapeGroup",
      "id": "84A60A75-C9ED-4CE0-A909-67A2833EFE5C"
    },
    {
      "class": "text",
      "id": "501BB94D-F606-45FA-9DD4-A633A7BE819B"
    }
  ],
  "name": "Group 5",
  "nameIsFixed": false,
  "resizingConstraint": 63,
  "resizingType": 0,
  "rotation": 0,
  "shouldBreakMaskChain": false,
  "style": {
    "_class": "style",
    "endDecorationType": 0,
    "miterLimit": 10,
    "startDecorationType": 0
  },
  "userInfo": {
    "com.animaapp.stc-sketch-plugin": {
      "kModelPropertiesKey": {
      }
    }
  }
}