{
  "_class": "shapePath",
  "booleanOperation": -1,
  "do_objectID": "18D3EAD9-C405-47A9-9291-50F49990083D",
  "edited": true,
  "exportOptions": {
    "_class": "exportOptions",
    "exportFormats": [
    ],
    "includedLayerIds": [
    ],
    "layerOptions": 0,
    "shouldTrim": false
  },
  "frame": {
    "_class": "rect",
    "constrainProportions": false,
    "height": 32.29200000000001,
    "width": 27.43199999999999,
    "x": 65.91600000000003,
    "y": 1.439999999999998
  },
  "isFlippedHorizontal": false,
  "isFlippedVertical": false,
  "isLocked": false,
  "isVisible": true,
  "layerListExpandedType": 0,
  "name": "Path",
  "nameIsFixed": false,
  "path": {
    "_class": "path",
    "isClosed": true,
    "pointRadiusBehaviour": 1,
    "points": [
      {
        "_class": "curvePoint",
        "cornerRadius": 0,
        "curveFrom": "{0.051181102362204613, 0.24080267558528431}",
        "curveMode": 1,
        "curveTo": "{0.051181102362204613, 0.24080267558528431}",
        "hasCurveFrom": false,
        "hasCurveTo": false,
        "point": "{0.051181102362204613, 0.24080267558528431}"
      },
      {
        "_class": "curvePoint",
        "cornerRadius": 0,
        "curveFrom": "{0.37795275590551181, 0.24080267558528431}",
        "curveMode": 1,
        "curveTo": "{0.37795275590551181, 0.24080267558528431}",
        "hasCurveFrom": false,
        "hasCurveTo": false,
        "point": "{0.37795275590551181, 0.24080267558528431}"
      },
      {
        "_class": "curvePoint",
        "cornerRadius": 0,
        "curveFrom": "{0.37795275590551181, 0.28093645484949836}",
        "curveMode": 1,
        "curveTo": "{0.37795275590551181, 0.28093645484949836}",
        "hasCurveFrom": false,
        "hasCurveTo": false,
        "point": "{0.37795275590551181, 0.28093645484949836}"
      },
      {
        "_class": "curvePoint",
        "cornerRadius": 0,
        "curveFrom": "{0.09973753280839863, 0.28093645484949836}",
        "curveMode": 1,
        "curveTo": "{0.09973753280839863, 0.28093645484949836}",
        "hasCurveFrom": false,
        "hasCurveTo": false,
        "point": "{0.09973753280839863, 0.28093645484949836}"
      },
      {
        "_class": "curvePoint",
        "cornerRadius": 0,
        "curveFrom": "{0.09973753280839863, 0.39353400222965434}",
        "curveMode": 1,
        "curveTo": "{0.09973753280839863, 0.39353400222965434}",
        "hasCurveFrom": false,
        "hasCurveTo": false,
        "point": "{0.09973753280839863, 0.39353400222965434}"
      },
      {
        "_class": "curvePoint",
        "cornerRadius": 0,
        "curveFrom": "{0.37795275590551181, 0.39353400222965434}",
        "curveMode": 1,
        "curveTo": "{0.37795275590551181, 0.39353400222965434}",
        "hasCurveFrom": false,
        "hasCurveTo": false,
        "point": "{0.37795275590551181, 0.39353400222965434}"
      },
      {
        "_class": "curvePoint",
        "cornerRadius": 0,
        "curveFrom": "{0.37795275590551181, 0.43366778149386848}",
        "curveMode": 1,
        "curveTo": "{0.37795275590551181, 0.43366778149386848}",
        "hasCurveFrom": false,
        "hasCurveTo": false,
        "point": "{0.37795275590551181, 0.43366778149386848}"
      },
      {
        "_class": "curvePoint",
        "cornerRadius": 0,
        "curveFrom": "{0.045931758530183414, 0.43366778149386848}",
        "curveMode": 1,
        "curveTo": "{0.045931758530183414, 0.43366778149386848}",
        "hasCurveFrom": false,
        "hasCurveTo": false,
        "point": "{0.045931758530183414, 0.43366778149386848}"
      },
      {
        "_class": "curvePoint",
        "cornerRadius": 0,
        "curveFrom": "{0.045931758530183414, 0.55964325529542913}",
        "curveMode": 1,
        "curveTo": "{0.045931758530183414, 0.55964325529542913}",
        "hasCurveFrom": false,
        "hasCurveTo": false,
        "point": "{0.045931758530183414, 0.55964325529542913}"
      },
      {
        "_class": "curvePoint",
        "cornerRadius": 0,
        "curveFrom": "{0.37795275590551181, 0.55964325529542913}",
        "curveMode": 1,
        "curveTo": "{0.37795275590551181, 0.55964325529542913}",
        "hasCurveFrom": false,
        "hasCurveTo": false,
        "point": "{0.37795275590551181, 0.55964325529542913}"
      },
      {
        "_class": "curvePoint",
        "cornerRadius": 0,
        "curveFrom": "{0.37795275590551181, 0.60646599777034549}",
        "curveMode": 1,
        "curveTo": "{0.37795275590551181, 0.60646599777034549}",
        "hasCurveFrom": false,
        "hasCurveTo": false,
        "point": "{0.37795275590551181, 0.60646599777034549}"
      },
      {
        "_class": "curvePoint",
        "cornerRadius": 0,
        "curveFrom": "{0.023622047244093322, 0.60646599777034549}",
        "curveMode": 1,
        "curveTo": "{0.023622047244093322, 0.60646599777034549}",
        "hasCurveFrom": false,
        "hasCurveTo": false,
        "point": "{0.023622047244093322, 0.60646599777034549}"
      },
      {
        "_class": "curvePoint",
        "cornerRadius": 0,
        "curveFrom": "{0.023622047244093322, 0.73913043478260865}",
        "curveMode": 1,
        "curveTo": "{0.023622047244093322, 0.73913043478260865}",
        "hasCurveFrom": false,
        "hasCurveTo": false,
        "point": "{0.023622047244093322, 0.73913043478260865}"
      },
      {
        "_class": "curvePoint",
        "cornerRadius": 0,
        "curveFrom": "{0.20603674540682376, 0.79152731326644366}",
        "curveMode": 4,
        "curveTo": "{0.2664041994750655, 0.73913043478260865}",
        "hasCurveFrom": true,
        "hasCurveTo": false,
        "point": "{0.2664041994750655, 0.73913043478260865}"
      },
      {
        "_class": "curvePoint",
        "cornerRadius": 0,
        "curveFrom": "{0, 0.87290969899665538}",
        "curveMode": 4,
        "curveTo": "{0.085301837270340339, 0.84280936454849498}",
        "hasCurveFrom": false,
        "hasCurveTo": true,
        "point": "{0, 0.87290969899665538}"
      },
      {
        "_class": "curvePoint",
        "cornerRadius": 0,
        "curveFrom": "{0.24015748031496051, 0.96098104793756955}",
        "curveMode": 4,
        "curveTo": "{0.12204724409448768, 1}",
        "hasCurveFrom": true,
        "hasCurveTo": false,
        "point": "{0.12204724409448768, 1}"
      },
      {
        "_class": "curvePoint",
        "cornerRadius": 0,
        "curveFrom": "{0.58267716535433023, 0.86510590858416947}",
        "curveMode": 4,
        "curveTo": "{0.41207349081364752, 0.85953177257525082}",
        "hasCurveFrom": true,
        "hasCurveTo": true,
        "point": "{0.49868766404199522, 0.78037904124860635}"
      },
      {
        "_class": "curvePoint",
        "cornerRadius": 0,
        "curveFrom": "{0.87926509186351764, 1}",
        "curveMode": 4,
        "curveTo": "{0.7388451443569547, 0.95317725752508364}",
        "hasCurveFrom": false,
        "hasCurveTo": true,
        "point": "{0.87926509186351764, 1}"
      },
      {
        "_class": "curvePoint",
        "cornerRadius": 0,
        "curveFrom": "{0.92257217847769046, 0.84280936454849498}",
        "curveMode": 4,
        "curveTo": "{1, 0.87290969899665538}",
        "hasCurveFrom": true,
        "hasCurveTo": false,
        "point": "{1, 0.87290969899665538}"
      },
      {
        "_class": "curvePoint",
        "cornerRadius": 0,
        "curveFrom": "{0.73490813648293984, 0.73913043478260865}",
        "curveMode": 4,
        "curveTo": "{0.79921259842519643, 0.80044593088071347}",
        "hasCurveFrom": false,
        "hasCurveTo": true,
        "point": "{0.73490813648293984, 0.73913043478260865}"
      },
      {
        "_class": "curvePoint",
        "cornerRadius": 0,
        "curveFrom": "{0.97769028871391095, 0.73913043478260865}",
        "curveMode": 1,
        "curveTo": "{0.97769028871391095, 0.73913043478260865}",
        "hasCurveFrom": false,
        "hasCurveTo": false,
        "point": "{0.97769028871391095, 0.73913043478260865}"
      },
      {
        "_class": "curvePoint",
        "cornerRadius": 0,
        "curveFrom": "{0.97769028871391095, 0.60646599777034549}",
        "curveMode": 1,
        "curveTo": "{0.97769028871391095, 0.60646599777034549}",
        "hasCurveFrom": false,
        "hasCurveTo": false,
        "point": "{0.97769028871391095, 0.60646599777034549}"
      },
      {
        "_class": "curvePoint",
        "cornerRadius": 0,
        "curveFrom": "{0.61811023622047234, 0.60646599777034549}",
        "curveMode": 1,
        "curveTo": "{0.61811023622047234, 0.60646599777034549}",
        "hasCurveFrom": false,
        "hasCurveTo": false,
        "point": "{0.61811023622047234, 0.60646599777034549}"
      },
      {
        "_class": "curvePoint",
        "cornerRadius": 0,
        "curveFrom": "{0.61811023622047234, 0.55964325529542913}",
        "curveMode": 1,
        "curveTo": "{0.61811023622047234, 0.55964325529542913}",
        "hasCurveFrom": false,
        "hasCurveTo": false,
        "point": "{0.61811023622047234, 0.55964325529542913}"
      },
      {
        "_class": "curvePoint",
        "cornerRadius": 0,
        "curveFrom": "{0.95144356955380593, 0.55964325529542913}",
        "curveMode": 1,
        "curveTo": "{0.95144356955380593, 0.55964325529542913}",
        "hasCurveFrom": false,
        "hasCurveTo": false,
        "point": "{0.95144356955380593, 0.55964325529542913}"
      },
      {
        "_class": "curvePoint",
        "cornerRadius": 0,
        "curveFrom": "{0.95144356955380593, 0.43366778149386848}",
        "curveMode": 1,
        "curveTo": "{0.95144356955380593, 0.43366778149386848}",
        "hasCurveFrom": false,
        "hasCurveTo": false,
        "point": "{0.95144356955380593, 0.43366778149386848}"
      },
      {
        "_class": "curvePoint",
        "cornerRadius": 0,
        "curveFrom": "{0.61811023622047234, 0.43366778149386848}",
        "curveMode": 1,
        "curveTo": "{0.61811023622047234, 0.43366778149386848}",
        "hasCurveFrom": false,
        "hasCurveTo": false,
        "point": "{0.61811023622047234, 0.43366778149386848}"
      },
      {
        "_class": "curvePoint",
        "cornerRadius": 0,
        "curveFrom": "{0.61811023622047234, 0.39353400222965434}",
        "curveMode": 1,
        "curveTo": "{0.61811023622047234, 0.39353400222965434}",
        "hasCurveFrom": false,
        "hasCurveTo": false,
        "point": "{0.61811023622047234, 0.39353400222965434}"
      },
      {
        "_class": "curvePoint",
        "cornerRadius": 0,
        "curveFrom": "{0.8923884514435696, 0.39353400222965434}",
        "curveMode": 1,
        "curveTo": "{0.8923884514435696, 0.39353400222965434}",
        "hasCurveFrom": false,
        "hasCurveTo": false,
        "point": "{0.8923884514435696, 0.39353400222965434}"
      },
      {
        "_class": "curvePoint",
        "cornerRadius": 0,
        "curveFrom": "{0.8923884514435696, 0.28093645484949836}",
        "curveMode": 1,
        "curveTo": "{0.8923884514435696, 0.28093645484949836}",
        "hasCurveFrom": false,
        "hasCurveTo": false,
        "point": "{0.8923884514435696, 0.28093645484949836}"
      },
      {
        "_class": "curvePoint",
        "cornerRadius": 0,
        "curveFrom": "{0.61811023622047234, 0.28093645484949836}",
        "curveMode": 1,
        "curveTo": "{0.61811023622047234, 0.28093645484949836}",
        "hasCurveFrom": false,
        "hasCurveTo": false,
        "point": "{0.61811023622047234, 0.28093645484949836}"
      },
      {
        "_class": "curvePoint",
        "cornerRadius": 0,
        "curveFrom": "{0.61811023622047234, 0.24080267558528431}",
        "curveMode": 1,
        "curveTo": "{0.61811023622047234, 0.24080267558528431}",
        "hasCurveFrom": false,
        "hasCurveTo": false,
        "point": "{0.61811023622047234, 0.24080267558528431}"
      },
      {
        "_class": "curvePoint",
        "cornerRadius": 0,
        "curveFrom": "{0.94225721784776884, 0.24080267558528431}",
        "curveMode": 1,
        "curveTo": "{0.94225721784776884, 0.24080267558528431}",
        "hasCurveFrom": false,
        "hasCurveTo": false,
        "point": "{0.94225721784776884, 0.24080267558528431}"
      },
      {
        "_class": "curvePoint",
        "cornerRadius": 0,
        "curveFrom": "{0.94225721784776884, 0.11482720178372344}",
        "curveMode": 1,
        "curveTo": "{0.94225721784776884, 0.11482720178372344}",
        "hasCurveFrom": false,
        "hasCurveTo": false,
        "point": "{0.94225721784776884, 0.11482720178372344}"
      },
      {
        "_class": "curvePoint",
        "cornerRadius": 0,
        "curveFrom": "{0.78477690288713919, 0.11482720178372344}",
        "curveMode": 1,
        "curveTo": "{0.78477690288713919, 0.11482720178372344}",
        "hasCurveFrom": false,
        "hasCurveTo": false,
        "point": "{0.78477690288713919, 0.11482720178372344}"
      },
      {
        "_class": "curvePoint",
        "cornerRadius": 0,
        "curveFrom": "{0.83989501312335968, 0}",
        "curveMode": 1,
        "curveTo": "{0.83989501312335968, 0}",
        "hasCurveFrom": false,
        "hasCurveTo": false,
        "point": "{0.83989501312335968, 0}"
      },
      {
        "_class": "curvePoint",
        "cornerRadius": 0,
        "curveFrom": "{0.62860892388451362, 0}",
        "curveMode": 1,
        "curveTo": "{0.62860892388451362, 0}",
        "hasCurveFrom": false,
        "hasCurveTo": false,
        "point": "{0.62860892388451362, 0}"
      },
      {
        "_class": "curvePoint",
        "cornerRadius": 0,
        "curveFrom": "{0.57611548556430381, 0.11482720178372344}",
        "curveMode": 1,
        "curveTo": "{0.57611548556430381, 0.11482720178372344}",
        "hasCurveFrom": false,
        "hasCurveTo": false,
        "point": "{0.57611548556430381, 0.11482720178372344}"
      },
      {
        "_class": "curvePoint",
        "cornerRadius": 0,
        "curveFrom": "{0.418635170603674, 0.11482720178372344}",
        "curveMode": 1,
        "curveTo": "{0.418635170603674, 0.11482720178372344}",
        "hasCurveFrom": false,
        "hasCurveTo": false,
        "point": "{0.418635170603674, 0.11482720178372344}"
      },
      {
        "_class": "curvePoint",
        "cornerRadius": 0,
        "curveFrom": "{0.36614173228346408, 0}",
        "curveMode": 1,
        "curveTo": "{0.36614173228346408, 0}",
        "hasCurveFrom": false,
        "hasCurveTo": false,
        "point": "{0.36614173228346408, 0}"
      },
      {
        "_class": "curvePoint",
        "cornerRadius": 0,
        "curveFrom": "{0.15485564304461913, 0}",
        "curveMode": 1,
        "curveTo": "{0.15485564304461913, 0}",
        "hasCurveFrom": false,
        "hasCurveTo": false,
        "point": "{0.15485564304461913, 0}"
      },
      {
        "_class": "curvePoint",
        "cornerRadius": 0,
        "curveFrom": "{0.20866141732283436, 0.11482720178372344}",
        "curveMode": 1,
        "curveTo": "{0.20866141732283436, 0.11482720178372344}",
        "hasCurveFrom": false,
        "hasCurveTo": false,
        "point": "{0.20866141732283436, 0.11482720178372344}"
      },
      {
        "_class": "curvePoint",
        "cornerRadius": 0,
        "curveFrom": "{0.051181102362204613, 0.11482720178372344}",
        "curveMode": 1,
        "curveTo": "{0.051181102362204613, 0.11482720178372344}",
        "hasCurveFrom": false,
        "hasCurveTo": false,
        "point": "{0.051181102362204613, 0.11482720178372344}"
      }
    ]
  },
  "resizingConstraint": 63,
  "resizingType": 0,
  "rotation": 0,
  "shouldBreakMaskChain": false
}