{
  "_class": "shapePath",
  "booleanOperation": 0,
  "do_objectID": "A0519E98-0E94-4E1A-893B-D3E2CFAE5937",
  "edited": true,
  "exportOptions": {
    "_class": "exportOptions",
    "exportFormats": [
    ],
    "includedLayerIds": [
    ],
    "layerOptions": 0,
    "shouldTrim": false
  },
  "frame": {
    "_class": "rect",
    "constrainProportions": false,
    "height": 15.16495177158321,
    "width": 8.891151564961936,
    "x": 6,
    "y": 13.24533338390802
  },
  "isFlippedHorizontal": false,
  "isFlippedVertical": false,
  "isLocked": false,
  "isVisible": true,
  "layerListExpandedType": 0,
  "name": "Path 4",
  "nameIsFixed": false,
  "path": {
    "_class": "path",
    "isClosed": true,
    "pointRadiusBehaviour": 1,
    "points": [
      {
        "_class": "curvePoint",
        "cornerRadius": 0,
        "curveFrom": "{0.4533800794589401, 0.50000000000000011}",
        "curveMode": 1,
        "curveTo": "{0.4533800794589401, 0.50000000000000011}",
        "hasCurveFrom": false,
        "hasCurveTo": false,
        "point": "{0.4533800794589401, 0.50000000000000011}"
      },
      {
        "_class": "curvePoint",
        "cornerRadius": 0,
        "curveFrom": "{1, 0.1353503139682912}",
        "curveMode": 1,
        "curveTo": "{1, 0.1353503139682912}",
        "hasCurveFrom": false,
        "hasCurveTo": false,
        "point": "{1, 0.1353503139682912}"
      },
      {
        "_class": "curvePoint",
        "cornerRadius": 0,
        "curveFrom": "{0.74951376825472915, 0}",
        "curveMode": 1,
        "curveTo": "{0.74951376825472915, 0}",
        "hasCurveFrom": false,
        "hasCurveTo": false,
        "point": "{0.74951376825472915, 0}"
      },
      {
        "_class": "curvePoint",
        "cornerRadius": 0,
        "curveFrom": "{0, 0.49999999999999994}",
        "curveMode": 1,
        "curveTo": "{0, 0.49999999999999994}",
        "hasCurveFrom": false,
        "hasCurveTo": false,
        "point": "{0, 0.49999999999999994}"
      },
      {
        "_class": "curvePoint",
        "cornerRadius": 0,
        "curveFrom": "{0.74951376825472915, 1}",
        "curveMode": 1,
        "curveTo": "{0.74951376825472915, 1}",
        "hasCurveFrom": false,
        "hasCurveTo": false,
        "point": "{0.74951376825472915, 1}"
      },
      {
        "_class": "curvePoint",
        "cornerRadius": 0,
        "curveFrom": "{1, 0.86464968603170878}",
        "curveMode": 1,
        "curveTo": "{1, 0.86464968603170878}",
        "hasCurveFrom": false,
        "hasCurveTo": false,
        "point": "{1, 0.86464968603170878}"
      }
    ]
  },
  "resizingConstraint": 63,
  "resizingType": 0,
  "rotation": 0,
  "shouldBreakMaskChain": false
}